README.md
setup.cfg
setup.py
LambdaQuery/__init__.py
LambdaQuery/do_notation.py
LambdaQuery/expr.py
LambdaQuery/functions.py
LambdaQuery/misc.py
LambdaQuery/query.py
LambdaQuery/reroute.py
LambdaQuery/sql.py
lambdaquery.egg-info/PKG-INFO
lambdaquery.egg-info/SOURCES.txt
lambdaquery.egg-info/dependency_links.txt
lambdaquery.egg-info/requires.txt
lambdaquery.egg-info/top_level.txt