Metadata-Version: 1.2
Name: lambdaquery
Version: 0.1.2
Summary: Composable SQL in Pure Python
Home-page: UNKNOWN
Author: Chong Wang
Author-email: chonw89@gmail.com
License: MIT
Keywords: databases query sql orm
Platform: UNKNOWN
Requires-Python: >=3.6
